.gitignore
MANIFEST.in
README.rst
bootstrap.py
buildout.cfg
setup.py
collective/__init__.py
collective.js.mousewheel.egg-info/PKG-INFO
collective.js.mousewheel.egg-info/SOURCES.txt
collective.js.mousewheel.egg-info/dependency_links.txt
collective.js.mousewheel.egg-info/entry_points.txt
collective.js.mousewheel.egg-info/namespace_packages.txt
collective.js.mousewheel.egg-info/not-zip-safe
collective.js.mousewheel.egg-info/requires.txt
collective.js.mousewheel.egg-info/top_level.txt
collective/js/__init__.py
collective/js/mousewheel/__init__.py
collective/js/mousewheel/configure.zcml
collective/js/mousewheel/profiles/default/jsregistry.xml
collective/js/mousewheel/profiles/default/metadata.xml
collective/js/mousewheel/resources/jquery.mousewheel.js
collective/js/mousewheel/resources/jquery.mousewheel.min.js
docs/HISTORY.txt