Metadata-Version: 1.0
Name: collective.js.mousewheel
Version: 1.0
Summary: Add JQuery Mousewheel plugin to the Plone CMS resource registry
Home-page: https://github.com/collective/collective.js.mousewheel
Author: JeanMichel FRANCOIS aka toutpt
Author-email: toutpt@gmail.com
License: GPL
Platform: UNKNOWN
Classifier: Framework :: Plone
Classifier: Framework :: Plone :: 4.0
Classifier: Framework :: Plone :: 4.1
Classifier: Programming Language :: Python
